COPYING
MANIFEST.in
README.rst
buildout.cfg
setup.py
version.txt
xbob/__init__.py
xbob.db.casme2.egg-info/PKG-INFO
xbob.db.casme2.egg-info/SOURCES.txt
xbob.db.casme2.egg-info/dependency_links.txt
xbob.db.casme2.egg-info/entry_points.txt
xbob.db.casme2.egg-info/namespace_packages.txt
xbob.db.casme2.egg-info/not-zip-safe
xbob.db.casme2.egg-info/requires.txt
xbob.db.casme2.egg-info/top_level.txt
xbob/db/__init__.py
xbob/db/casme2/__init__.py
xbob/db/casme2/create.py
xbob/db/casme2/driver.py
xbob/db/casme2/models.py
xbob/db/casme2/query.py
xbob/db/casme2/test.py
xbob/db/casme2/version.py